amis_rest/__init__.py
amis_rest/admin.py
amis_rest/apps.py
amis_rest/exceptions.py
amis_rest/models.py
amis_rest/pagination.py
amis_rest/responses.py
amis_rest/tests.py
amis_rest/utils.py
amis_rest/views.py
django_amis-0.2.0.dist-info/licenses/LICENSE
django_amis-0.2.0.dist-info/METADATA
django_amis-0.2.0.dist-info/WHEEL
django_amis-0.2.0.dist-info/top_level.txt
django_amis-0.2.0.dist-info/RECORD
