Metadata-Version: 2.4
Name: django-amis
Version: 0.2.0
Summary: Django AMIS 风格的 RESTful API 工具包
Author-email: liuli <525334480@qq.com>
License: MIT
Classifier: Framework :: Django
Classifier: Framework :: Django :: 5.2
Classifier: Intended Audience :: Developers
Classifier: License :: OSI Approved :: MIT License
Classifier: Programming Language :: Python :: 3
Classifier: Programming Language :: Python :: 3.12
Classifier: Topic :: Software Development :: Libraries :: Python Modules
Requires-Python: >=3.12
License-File: LICENSE
Requires-Dist: django>=5.2.6
Requires-Dist: django-amis-render>=0.0.8
Requires-Dist: django-filter>=25.1
Requires-Dist: djangorestframework>=3.16.1
Requires-Dist: markdown>=3.9
Requires-Dist: openpyxl>=3.1.5
Requires-Dist: pandas>=2.3.2
Dynamic: license-file
